histextractor/__init__.py
histextractor/main.py
histextractor/prompts.py
histextractor-2025.12.21165426.dist-info/METADATA
histextractor-2025.12.21165426.dist-info/WHEEL
histextractor-2025.12.21165426.dist-info/top_level.txt
histextractor-2025.12.21165426.dist-info/RECORD
