Metadata-Version: 2.4
Name: histextractor
Version: 2025.12.21165426
Summary: A new package that extracts and structures key historical facts and insights from textual descriptions of historical events, such as the Lend-Lease program during World War II. The package takes a tex
Author-email: histextractor <hi@eugene.plus>
License: MIT
Project-URL: Homepage, https://github.com/chigwell/histextractor
Requires-Python: >=3.9
Requires-Dist: langchain-llm7>=0.0.0
Requires-Dist: llmatch-messages>=0.0.0
Requires-Dist: langchain-core>=0.3.0
